hyp3_metadata/__init__.py
hyp3_metadata/__main__.py
hyp3_metadata/create.py
hyp3_metadata/insar.py
hyp3_metadata/rtc.py
hyp3_metadata/util.py
hyp3_metadata/_depreciated/GAMMA/InSAR/README_InSAR_GAMMA.txt
hyp3_metadata/_depreciated/GAMMA/RTC/README_RTC_GAMMA.txt
hyp3_metadata/_depreciated/GAMMA/RTC/RTC_GAMMA_Template.xml
hyp3_metadata/_depreciated/GAMMA/RTC/RTC_GAMMA_Template_color_png.xml
hyp3_metadata/_depreciated/GAMMA/RTC/RTC_GAMMA_Template_dem_EUDEM.xml
hyp3_metadata/_depreciated/GAMMA/RTC/RTC_GAMMA_Template_dem_GIMP.xml
hyp3_metadata/_depreciated/GAMMA/RTC/RTC_GAMMA_Template_dem_NED.xml
hyp3_metadata/_depreciated/GAMMA/RTC/RTC_GAMMA_Template_dem_REMA.xml
hyp3_metadata/_depreciated/GAMMA/RTC/RTC_GAMMA_Template_dem_SRTM.xml
hyp3_metadata/_depreciated/GAMMA/RTC/RTC_GAMMA_Template_grayscale_png.xml
hyp3_metadata/_depreciated/GAMMA/RTC/RTC_GAMMA_Template_inc.xml
hyp3_metadata/_depreciated/GAMMA/RTC/RTC_GAMMA_Template_ls.xml
hyp3_metadata/_depreciated/GAMMA/TCD/README_TCD_GAMMA.txt
hyp3_metadata/_depreciated/ISCE/InSAR/README_InSAR_ISCE.txt
hyp3_metadata/_depreciated/S1TBX/RTC/README_RTC_S1TBX.txt
hyp3_metadata/_depreciated/S1TBX/RTC/RTC_S1TBX_Template.xml
hyp3_metadata/_depreciated/S1TBX/RTC/RTC_S1TBX_Template_color_png.xml
hyp3_metadata/_depreciated/S1TBX/RTC/RTC_S1TBX_Template_dem_EUDEM.xml
hyp3_metadata/_depreciated/S1TBX/RTC/RTC_S1TBX_Template_dem_GIMP.xml
hyp3_metadata/_depreciated/S1TBX/RTC/RTC_S1TBX_Template_dem_NED.xml
hyp3_metadata/_depreciated/S1TBX/RTC/RTC_S1TBX_Template_dem_REMA.xml
hyp3_metadata/_depreciated/S1TBX/RTC/RTC_S1TBX_Template_dem_SRTM.xml
hyp3_metadata/_depreciated/S1TBX/RTC/RTC_S1TBX_Template_grayscale_png.xml
hyp3_metadata/_depreciated/S1TBX/RTC/RTC_S1TBX_Template_inc.xml
hyp3_metadata/_depreciated/S1TBX/RTC/RTC_S1TBX_Template_ls.xml
hyp3_metadata/data/__init__.py
hyp3_metadata/data/insar/insar_amp.tif
hyp3_metadata/data/insar/insar_color_phase.png
hyp3_metadata/data/insar/insar_color_phase.png.aux.xml
hyp3_metadata-1.3.0.dist-info/LICENSE
hyp3_metadata-1.3.0.dist-info/METADATA
hyp3_metadata-1.3.0.dist-info/WHEEL
hyp3_metadata-1.3.0.dist-info/top_level.txt
hyp3_metadata-1.3.0.dist-info/RECORD
