Metadata-Version: 2.1
Name: hyp3-metadata
Version: 1.3.0
Summary: Package for generating HyP3 products' metadata
Home-page: https://github.com/ASFHyP3/hyp3-metadata-templates
Author: ASF APD/Tools Team
Author-email: uaf-asf-apd@alaska.edu
License: BSD
Platform: UNKNOWN
Classifier: Intended Audience :: Science/Research
Classifier: License :: OSI Approved :: BSD License
Classifier: Natural Language :: English
Classifier: Programming Language :: Python :: 3
Classifier: Programming Language :: Python :: 3.6
Requires-Python: ~=3.6
License-File: LICENSE
Requires-Dist: importlib-metadata
Requires-Dist: jinja2
Requires-Dist: gdal
Requires-Dist: pillow
Requires-Dist: python-dateutil
Provides-Extra: develop
Requires-Dist: pytest ; extra == 'develop'
Requires-Dist: pytest-cov ; extra == 'develop'
